{
  "generatedAtUtc": "2026-05-28T23:36:44.620Z",
  "dataSource": "Twelve Data",
  "timezoneUsedForDailyBars": "Provider daily bars",
  "symbolsIncluded": [
    "EUR/USD",
    "GBP/USD",
    "AUD/USD",
    "USD/CAD"
  ],
  "staleAfterMinutes": 90,
  "markets": [
    {
      "symbol": "EUR/USD",
      "price": 1.16512,
      "previousDayHigh": 1.16539,
      "previousDayLow": 1.16486,
      "bias": "long",
      "contextLine": "Trading inside previous day range",
      "buySetup": {
        "title": "PDL reclaim / PDH break hold",
        "entry": "Watch live structure around 1.16512",
        "target": "Move toward 1.16539"
      },
      "sellSetup": {
        "title": "Failed hold / rejection short",
        "entry": "Watch live structure around 1.16512",
        "target": "Move toward 1.16486"
      }
    },
    {
      "symbol": "GBP/USD",
      "price": 1.34443,
      "previousDayHigh": 1.34475,
      "previousDayLow": 1.34396,
      "bias": "long",
      "contextLine": "Trading inside previous day range",
      "buySetup": {
        "title": "PDL reclaim / PDH break hold",
        "entry": "Watch live structure around 1.34443",
        "target": "Move toward 1.34475"
      },
      "sellSetup": {
        "title": "Failed hold / rejection short",
        "entry": "Watch live structure around 1.34443",
        "target": "Move toward 1.34396"
      }
    },
    {
      "symbol": "AUD/USD",
      "price": 0.71633,
      "previousDayHigh": 0.71662,
      "previousDayLow": 0.71559,
      "bias": "long",
      "contextLine": "Trading inside previous day range",
      "buySetup": {
        "title": "PDL reclaim / PDH break hold",
        "entry": "Watch live structure around 0.71633",
        "target": "Move toward 0.71662"
      },
      "sellSetup": {
        "title": "Failed hold / rejection short",
        "entry": "Watch live structure around 0.71633",
        "target": "Move toward 0.71559"
      }
    },
    {
      "symbol": "USD/CAD",
      "price": 1.37832,
      "previousDayHigh": 1.37896,
      "previousDayLow": 1.37801,
      "bias": "short",
      "contextLine": "Trading inside previous day range",
      "buySetup": {
        "title": "Countertrend reclaim",
        "entry": "Watch live structure around 1.37832",
        "target": "Move toward 1.37896"
      },
      "sellSetup": {
        "title": "PDH rejection / PDL break hold",
        "entry": "Watch live structure around 1.37832",
        "target": "Move toward 1.37801"
      }
    }
  ]
}
